{"id": "random_97", "category": "random", "width": 14, "height": 22, "palette": ["#be4a2f", "#d77643", "#3e8948", "#265c42", "#63c74d", "#193c3e", "#b86f50", "#e4a672", "#3a4466"], "grid": [[0, 0, 0, 0, 1, 1, 2, 2, 2, 2, 0, 0, 0, 0], [0, 0, 0, 0, 1, 1, 2, 2, 2, 2, 0, 0, 0, 0], [0, 0, 0, 3, 4, 4, 4, 3, 3, 5, 3, 0, 0, 0], [0, 0, 0, 3, 4, 4, 4, 3, 3, 5, 3, 0, 0, 0], [0, 0, 0, 0, 6, 6, 6, 4, 4, 4, 0, 0, 0, 0], [0, 0, 0, 0, 4, 4, 3, 3, 5, 3, 0, 0, 0, 0], [0, 0, 0, 0, 4, 4, 3, 3, 5, 3, 0, 0, 0, 0], [0, 0, 0, 0, 4, 4, 3, 3, 5, 3, 0, 0, 0, 0], [0, 0, 0, 0, 4, 4, 3, 3, 5, 3, 0, 0, 0, 0], [4, 6, 6, 3, 4, 3, 3, 3, 3, 5, 5, 3, 3, 4], [4, 6, 6, 3, 4, 3, 3, 3, 3, 5, 5, 3, 3, 4], [4, 6, 6, 3, 4, 3, 3, 3, 3, 5, 5, 3, 3, 4], [4, 6, 7, 7, 8, 7, 8, 8, 8, 8, 8, 8, 8, 8], [4, 6, 7, 7, 8, 7, 8, 9, 8, 8, 8, 9, 8, 8], [4, 6, 7, 7, 8, 7, 8, 8, 9, 8, 9, 8, 8, 8], [4, 6, 7, 7, 8, 7, 8, 8, 8, 9, 8, 8, 8, 8], [4, 6, 7, 7, 8, 7, 8, 8, 9, 8, 9, 8, 8, 8], [4, 6, 7, 7, 8, 7, 8, 9, 8, 8, 8, 9, 8, 8], [4, 6, 7, 7, 8, 7, 8, 8, 8, 8, 8, 8, 8, 8], [4, 6, 6, 3, 6, 6, 6, 6, 6, 4, 4, 6, 3, 4], [4, 6, 6, 3, 4, 4, 4, 4, 4, 3, 5, 4, 3, 4], [4, 6, 6, 3, 4, 3, 3, 3, 3, 3, 5, 3, 3, 4]]}